{
	"format_version": "1.10.0",
	"animation_controllers": {
"controller.animation.iceologer_ice": {
			
    "initial_state":"not_exploded",
   "states": {
       "not_exploded":{
           "transitions":[{ "explode": "q.is_on_ground" }]
         },
         "explode":{
           "on_entry": [
            "/event entity @e[type=better_on_bedrock:iceologer_iceblock_fall] explode"
        
        ],
            "transitions": [{"not_exploded":"!q.is_on_ground"}]
         }
   }
         }
        }
    }